cnvlib/__init__.py
cnvlib/_version.py
cnvlib/access.py
cnvlib/antitarget.py
cnvlib/autobin.py
cnvlib/batch.py
cnvlib/bintest.py
cnvlib/call.py
cnvlib/cluster.py
cnvlib/cmdutil.py
cnvlib/cnary.py
cnvlib/cnvkit.py
cnvlib/commands.py
cnvlib/core.py
cnvlib/coverage.py
cnvlib/descriptives.py
cnvlib/diagram.py
cnvlib/export.py
cnvlib/fix.py
cnvlib/heatmap.py
cnvlib/import_rna.py
cnvlib/importers.py
cnvlib/metrics.py
cnvlib/parallel.py
cnvlib/params.py
cnvlib/plots.py
cnvlib/reference.py
cnvlib/reports.py
cnvlib/rna.py
cnvlib/samutil.py
cnvlib/scatter.py
cnvlib/segfilters.py
cnvlib/segmetrics.py
cnvlib/smoothing.py
cnvlib/target.py
cnvlib/vary.py
cnvlib/segmentation/__init__.py
cnvlib/segmentation/cbs.py
cnvlib/segmentation/flasso.py
cnvlib/segmentation/haar.py
cnvlib/segmentation/hmm.py
cnvlib/segmentation/none.py
skgenome/__init__.py
skgenome/chromsort.py
skgenome/combiners.py
skgenome/gary.py
skgenome/intersect.py
skgenome/merge.py
skgenome/rangelabel.py
skgenome/subdivide.py
skgenome/subtract.py
skgenome/tabio/__init__.py
skgenome/tabio/bedio.py
skgenome/tabio/genepred.py
skgenome/tabio/gff.py
skgenome/tabio/picard.py
skgenome/tabio/seg.py
skgenome/tabio/seqdict.py
skgenome/tabio/tab.py
skgenome/tabio/textcoord.py
skgenome/tabio/util.py
skgenome/tabio/vcfio.py
skgenome/tabio/vcfsimple.py
CNVkit-0.9.10.dist-info/LICENSE
CNVkit-0.9.10.dist-info/METADATA
CNVkit-0.9.10.dist-info/WHEEL
CNVkit-0.9.10.dist-info/entry_points.txt
CNVkit-0.9.10.dist-info/top_level.txt
CNVkit-0.9.10.dist-info/RECORD
