Metadata-Version: 2.1
Name: CNVkit
Version: 0.9.10
Summary: Copy number variation toolkit for high-throughput sequencing.
Author-email: Eric Talevich <etal@users.noreply.github.com>
Maintainer-email: Eric Talevich <etal@users.noreply.github.com>
License: Apache-2.0
Project-URL: homepage, https://github.com/etal/cnvkit
Project-URL: documentation, https://readthedocs.org
Project-URL: repository, https://github.com/etal/cnvkit
Project-URL: changelog, https://github.com/me/spam/blob/master/CHANGELOG.md
Classifier: Development Status :: 4 - Beta
Classifier: Environment :: Console
Classifier: Intended Audience :: Science/Research
Classifier: Intended Audience :: Healthcare Industry
Classifier: License :: OSI Approved :: Apache Software License
Classifier: Operating System :: MacOS :: MacOS X
Classifier: Operating System :: POSIX
Classifier: Operating System :: POSIX :: Linux
Classifier: Operating System :: Unix
Classifier: Programming Language :: Python
Classifier: Programming Language :: Python :: 3
Classifier: Topic :: Scientific/Engineering
Classifier: Topic :: Scientific/Engineering :: Bio-Informatics
Classifier: Topic :: Scientific/Engineering :: Medical Science Apps.
Classifier: Topic :: Scientific/Engineering :: Visualization
Requires-Python: >=3.7
License-File: LICENSE
Requires-Dist: biopython (>=1.79)
Requires-Dist: matplotlib (>=3.5.1)
Requires-Dist: numpy (>=1.21.6)
Requires-Dist: pandas (>=1.3.5)
Requires-Dist: pomegranate (>=0.14.8)
Requires-Dist: pyfaidx (>=0.6.4)
Requires-Dist: pysam (>=0.17.0)
Requires-Dist: reportlab (>=3.6.8)
Requires-Dist: scikit-learn (>=1.0.2)
Requires-Dist: scipy (>=1.7.3)
Provides-Extra: test
Requires-Dist: pytest ; extra == 'test'
Requires-Dist: pytest-cov ; extra == 'test'
